pyinvert/__init__.py
pyinvert/pyinvert.py
pyinvert-0.0.1.dist-info/METADATA
pyinvert-0.0.1.dist-info/WHEEL
pyinvert-0.0.1.dist-info/licenses/LICENSE
pyinvert-0.0.1.dist-info/RECORD
