Metadata-Version: 2.1
Name: pyinvert
Version: 0.0.1
Summary: A simple invert function implementation using python and cv2
Project-URL: Homepage, https://github.com/garbage1010/invert
Project-URL: Bug Tracker, https://github.com/garbage1010/invert/issues
Author-email: Rory Meeduri <rory5827@outlook.com>
License-File: LICENSE
Classifier: License :: OSI Approved :: MIT License
Classifier: Operating System :: OS Independent
Classifier: Programming Language :: Python :: 3
Requires-Python: >=3.10
